db_manager/__init__.py
db_manager/dataframe.py
db_manager/manager.py
rpa_db_manager-0.1.0.dist-info/licenses/LICENSE
rpa_db_manager-0.1.0.dist-info/METADATA
rpa_db_manager-0.1.0.dist-info/WHEEL
rpa_db_manager-0.1.0.dist-info/top_level.txt
rpa_db_manager-0.1.0.dist-info/RECORD
