Metadata-Version: 2.4
Name: rpa-db-manager
Version: 0.1.0
Summary: Database manager for quick integration of Botcity RPA + Pandas Dataframes + SQLAlchemy for simple data persistance.
Author-email: Ausier Neto <ausierneto@gmail.com>
License: MIT License
Project-URL: Homepage, https://github.com/AusierNeto/automation-database-manager
Project-URL: Documentation, https://github.com/AusierNeto/automation-database-manager
Project-URL: Source, https://github.com/AusierNeto/automation-database-manager
Project-URL: Issues, https://github.com/AusierNeto/automation-database-manager/issues
Classifier: Programming Language :: Python :: 3
Classifier: License :: OSI Approved :: MIT License
Classifier: Operating System :: OS Independent
Requires-Python: >=3.9
License-File: LICENSE
Requires-Dist: sqlalchemy>=2.0.43
Requires-Dist: pandas>=2.3.3
Dynamic: license-file
